tacotron/__init__.py
tacotron/analysis.py
tacotron/audio_utils.py
tacotron/checkpoint.py
tacotron/checkpoint_handling.py
tacotron/dataloader.py
tacotron/eval_checkpoints.py
tacotron/globals.py
tacotron/hparams.py
tacotron/image_utils.py
tacotron/layers.py
tacotron/logger.py
tacotron/model.py
tacotron/model_checkpoint.py
tacotron/model_weights.py
tacotron/parser.py
tacotron/statistics.py
tacotron/stft.py
tacotron/synthesizer.py
tacotron/taco_stft.py
tacotron/training.py
tacotron/typing.py
tacotron/utils.py
tacotron/validation.py
tacotron/frontend/__init__.py
tacotron/frontend/arpa_symbols.py
tacotron/frontend/ipa_symbols.py
tacotron/frontend/main.py
tacotron/frontend/stress_detection.py
tacotron/frontend/tone_detection.py
tacotron_cli/__init__.py
tacotron_cli/analysis.py
tacotron_cli/argparse_helper.py
tacotron_cli/cli.py
tacotron_cli/defaults.py
tacotron_cli/eval_checkpoints.py
tacotron_cli/helper.py
tacotron_cli/inference.py
tacotron_cli/io.py
tacotron_cli/logging_configuration.py
tacotron_cli/mel_creation.py
tacotron_cli/textgrid_inference.py
tacotron_cli/training.py
tacotron_cli/validation.py
tacotron_cli/weights.py
tacotron_cli-0.0.5.dist-info/LICENSE
tacotron_cli-0.0.5.dist-info/METADATA
tacotron_cli-0.0.5.dist-info/WHEEL
tacotron_cli-0.0.5.dist-info/entry_points.txt
tacotron_cli-0.0.5.dist-info/top_level.txt
tacotron_cli-0.0.5.dist-info/RECORD
