Metadata-Version: 2.1
Name: tacotron-cli
Version: 0.0.5
Summary: Command-line interface (CLI) to train Tacotron 2 using .wav <=> .TextGrid pairs.
Author-email: Stefan Taubert <pypi@stefantaubert.com>
Maintainer-email: Stefan Taubert <pypi@stefantaubert.com>
License: MIT
Project-URL: Homepage, https://github.com/stefantaubert/tacotron
Project-URL: Issues, https://github.com/stefantaubert/tacotron/issues
Keywords: Text-to-speech,Speech synthesis,Corpus,Utils,Language,Linguistics
Classifier: Development Status :: 2 - Pre-Alpha
Classifier: Operating System :: OS Independent
Classifier: Operating System :: MacOS
Classifier: Operating System :: POSIX
Classifier: Operating System :: POSIX :: BSD
Classifier: Operating System :: POSIX :: Linux
Classifier: Operating System :: Unix
Classifier: Operating System :: Microsoft :: Windows
Classifier: Programming Language :: Python
Classifier: Programming Language :: Python :: 3
Classifier: Programming Language :: Python :: 3.8
Classifier: Programming Language :: Python :: 3.9
Classifier: Programming Language :: Python :: 3.10
Classifier: Programming Language :: Python :: 3.11
Classifier: License :: OSI Approved :: MIT License
Requires-Python: <3.12,>=3.8
License-File: LICENSE
Requires-Dist: numpy >=1.18.5
Requires-Dist: scipy >=1.8.0
Requires-Dist: tqdm >=4.63.0
Requires-Dist: torch >=2.0.0
Requires-Dist: pandas >=1.0.5
Requires-Dist: librosa >=0.10.0
Requires-Dist: plotly
Requires-Dist: scikit-image
Requires-Dist: matplotlib
Requires-Dist: scikit-learn
Requires-Dist: ordered-set >=4.1.0
Requires-Dist: speech-dataset-parser >=0.0.4
Requires-Dist: mel-cepstral-distance >=0.0.3
Requires-Dist: wget >=3.2
